vin_cli/__init__.py
vin_cli/cli/__init__.py
vin_cli/cli/main.py
vin_cli-0.1.0.dist-info/LICENSE
vin_cli-0.1.0.dist-info/METADATA
vin_cli-0.1.0.dist-info/WHEEL
vin_cli-0.1.0.dist-info/entry_points.txt
vin_cli-0.1.0.dist-info/RECORD
